Workbook

Sheet Resumo
B1: Dashboard financeiro — PME
B2: mar/2026 a set/2026 · 200 transações tratadas a partir de um export bruto simulado (ver README)
B4: RECEBIDO | E4: PAGO | H4: SALDO DE CAIXA
B5: ='Fluxo Mensal'!C12 -> 82976.55 | E5: ='Fluxo Mensal'!D12 -> 61639.3 | H5: ='Fluxo Mensal'!E12 -> 21337.25
B6: entrou no caixa (pago) | E6: saiu do caixa (pago) | H6: recebido − pago
B8: A RECEBER | E8: A PAGAR | H8: RESULTADO LÍQUIDO
B9: ='Contas a Pagar e Receber'!F5 -> 199712.9 | E9: ='Contas a Pagar e Receber'!F6 -> 177687.16 | H9: =DRE!C14 -> 61963.98
B10: pendente ou atrasado | E10: pendente ou atrasado | H10: receita − despesas (DRE)
B12: Fluxo de caixa mensal
B31: Abas desta planilha
B32: Fluxo Mensal | E32: entradas e saídas pagas mês a mês, saldo do mês e acumulado
B33: Contas a Pagar e Receber | E33: o que está pendente ou atrasado, com a lista de cada lado
B34: DRE | E34: receita, despesas por categoria e resultado líquido
B35: Dados | E35: as transações tratadas — base de todas as fórmulas; edite e os totais recalculam
B37: Dados simulados com sujeira proposital (categorias, datas, sinais e status) — o README do projeto mostra o tratamento e o relatório de qualidade de dados.

Sheet Dados
B1: Transações
B2: 200 lançamentos já tratados — a base de todas as fórmulas desta planilha: mude um valor ou um status aqui e os totais das outras abas recalculam.
B4: Data | C4: Descrição | D4: Categoria | E4: Tipo | F4: Valor | G4: Status
B5: 46110 | C5: Saída - Fornecedor Z | D5: Imposto | E5: Saída | F5: 849.83 | G5: Pendente
B6: 46111 | C6: Saída - Fornecedor Y | D6: Manutenção | E6: Saída | F6: 665.55 | G6: Pendente
B7: 46112 | C7: Saída - Fornecedor Y | D7: Salário | E7: Saída | F7: 3351.12 | G7: Pendente
B8: 46113 | C8: Entrada - Cliente B | D8: Venda de Serviço | E8: Entrada | F8: 796.61 | G8: Pago
B9: 46115 | C9: Entrada - Cliente A | D9: Venda de Serviço | E9: Entrada | F9: 3602.18 | G9: Atrasado
B10: 46115 | C10: Entrada - Cliente B | D10: Venda de Serviço | E10: Entrada | F10: 554.41 | G10: Atrasado
B11: 46116 | C11: Entrada - Cliente C | D11: Venda de Serviço | E11: Entrada | F11: 3367.37 | G11: Atrasado
B12: 46116 | C12: Entrada - Cliente A | D12: Venda de Serviço | E12: Entrada | F12: 3417.4 | G12: Atrasado
B13: 46117 | C13: Entrada - Cliente C | D13: Venda de Serviço | E13: Entrada | F13: 1974.84 | G13: Pendente
B14: 46117 | C14: Entrada - Cliente C | D14: Venda de Serviço | E14: Entrada | F14: 4647.99 | G14: Pendente
B15: 46119 | C15: Entrada - Cliente B | D15: Venda de Serviço | E15: Entrada | F15: 3579.1 | G15: Atrasado
B16: 46120 | C16: Entrada - Cliente A | D16: Venda de Serviço | E16: Entrada | F16: 1852.9 | G16: Pendente
... B204: 46290 | C204: Entrada - Cliente A | D204: Venda de Serviço | E204: Entrada | F204: 2782.36 | G204: Pendente

Sheet Fluxo Mensal
B1: Fluxo de caixa mensal
B2: mar/2026 a set/2026 · regime de caixa: só transações com status Pago (pendentes e atrasadas estão em Contas a Pagar e Receber)
B4: Mês | C4: Entradas | D4: Saídas | E4: Saldo do mês | F4: Saldo acumulado
B5: 46082 | C5: =SUMIFS(Dados!$F$5:$F$204,Dados!$E$5:$E$204,"Entrada",Dados!$G$5:$G$204,"Pago",Dados!$B$5:$B$204,">="&B5,Dados!$B$5:$B$204,"<"&EDATE(B5,1)) -> 0 | D5: =SUMIFS(Dados!$F$5:$F$204,Dados!$E$5:$E$204,"Saída",Dados!$G$5:$G$204,"Pago",Dados!$B$5:$B$204,">="&B5,Dados!$B$5:$B$204,"<"&EDATE(B5,1)) -> 0 | E5: =C5-D5 -> 0 | F5: =E5 -> 0
B6: 46113 | C6: =SUMIFS(Dados!$F$5:$F$204,Dados!$E$5:$E$204,"Entrada",Dados!$G$5:$G$204,"Pago",Dados!$B$5:$B$204,">="&B6,Dados!$B$5:$B$204,"<"&EDATE(B6,1)) -> 17510.88 | D6: =SUMIFS(Dados!$F$5:$F$204,Dados!$E$5:$E$204,"Saída",Dados!$G$5:$G$204,"Pago",Dados!$B$5:$B$204,">="&B6,Dados!$B$5:$B$204,"<"&EDATE(B6,1)) -> 3978.99 | E6: =C6-D6 -> 13531.89 | F6: =F5+E6 -> 13531.89
B7: 46143 | C7: =SUMIFS(Dados!$F$5:$F$204,Dados!$E$5:$E$204,"Entrada",Dados!$G$5:$G$204,"Pago",Dados!$B$5:$B$204,">="&B7,Dados!$B$5:$B$204,"<"&EDATE(B7,1)) -> 13227.69 | D7: =SUMIFS(Dados!$F$5:$F$204,Dados!$E$5:$E$204,"Saída",Dados!$G$5:$G$204,"Pago",Dados!$B$5:$B$204,">="&B7,Dados!$B$5:$B$204,"<"&EDATE(B7,1)) -> 9067.97 | E7: =C7-D7 -> 4159.72 | F7: =F6+E7 -> 17691.61
B8: 46174 | C8: =SUMIFS(Dados!$F$5:$F$204,Dados!$E$5:$E$204,"Entrada",Dados!$G$5:$G$204,"Pago",Dados!$B$5:$B$204,">="&B8,Dados!$B$5:$B$204,"<"&EDATE(B8,1)) -> 10106.95 | D8: =SUMIFS(Dados!$F$5:$F$204,Dados!$E$5:$E$204,"Saída",Dados!$G$5:$G$204,"Pago",Dados!$B$5:$B$204,">="&B8,Dados!$B$5:$B$204,"<"&EDATE(B8,1)) -> 0 | E8: =C8-D8 -> 10106.95 | F8: =F7+E8 -> 27798.56
B9: 46204 | C9: =SUMIFS(Dados!$F$5:$F$204,Dados!$E$5:$E$204,"Entrada",Dados!$G$5:$G$204,"Pago",Dados!$B$5:$B$204,">="&B9,Dados!$B$5:$B$204,"<"&EDATE(B9,1)) -> 15254.72 | D9: =SUMIFS(Dados!$F$5:$F$204,Dados!$E$5:$E$204,"Saída",Dados!$G$5:$G$204,"Pago",Dados!$B$5:$B$204,">="&B9,Dados!$B$5:$B$204,"<"&EDATE(B9,1)) -> 24986.93 | E9: =C9-D9 -> -9732.21 | F9: =F8+E9 -> 18066.35
B10: 46235 | C10: =SUMIFS(Dados!$F$5:$F$204,Dados!$E$5:$E$204,"Entrada",Dados!$G$5:$G$204,"Pago",Dados!$B$5:$B$204,">="&B10,Dados!$B$5:$B$204,"<"&EDATE(B10,1)) -> 14949.33 | D10: =SUMIFS(Dados!$F$5:$F$204,Dados!$E$5:$E$204,"Saída",Dados!$G$5:$G$204,"Pago",Dados!$B$5:$B$204,">="&B10,Dados!$B$5:$B$204,"<"&EDATE(B10,1)) -> 6810.78 | E10: =C10-D10 -> 8138.55 | F10: =F9+E10 -> 26204.9
B11: 46266 | C11: =SUMIFS(Dados!$F$5:$F$204,Dados!$E$5:$E$204,"Entrada",Dados!$G$5:$G$204,"Pago",Dados!$B$5:$B$204,">="&B11,Dados!$B$5:$B$204,"<"&EDATE(B11,1)) -> 11926.98 | D11: =SUMIFS(Dados!$F$5:$F$204,Dados!$E$5:$E$204,"Saída",Dados!$G$5:$G$204,"Pago",Dados!$B$5:$B$204,">="&B11,Dados!$B$5:$B$204,"<"&EDATE(B11,1)) -> 16794.63 | E11: =C11-D11 -> -4867.65 | F11: =F10+E11 -> 21337.25
B12: Total | C12: =SUM(C5:C11) -> 82976.55 | D12: =SUM(D5:D11) -> 61639.3 | E12: =SUM(E5:E11) -> 21337.25
B14: Entradas x saídas por mês
B32: Saldo acumulado

Sheet Contas a Pagar e Receber
B1: Contas a pagar e receber
B2: Transações com status Pendente ou Atrasado — o que ainda vai entrar e sair do caixa
B4: Em aberto | D4: Pendente | E4: Atrasado | F4: Total
B5: A receber (entradas) | D5: =SUMIFS(Dados!$F$5:$F$204,Dados!$E$5:$E$204,"Entrada",Dados!$G$5:$G$204,"Pendente") -> 86550.82 | E5: =SUMIFS(Dados!$F$5:$F$204,Dados!$E$5:$E$204,"Entrada",Dados!$G$5:$G$204,"Atrasado") -> 113162.08 | F5: =D5+E5 -> 199712.9
B6: A pagar (saídas) | D6: =SUMIFS(Dados!$F$5:$F$204,Dados!$E$5:$E$204,"Saída",Dados!$G$5:$G$204,"Pendente") -> 84201.8 | E6: =SUMIFS(Dados!$F$5:$F$204,Dados!$E$5:$E$204,"Saída",Dados!$G$5:$G$204,"Atrasado") -> 93485.36 | F6: =D6+E6 -> 177687.16
B7: Saldo em aberto (receber − pagar) | F7: =F5-F6 -> 22025.74
B10: Contas a receber em aberto (72)
B11: Data | C11: Descrição | D11: Categoria | E11: Valor | F11: Status
B12: 46115 | C12: Entrada - Cliente A | D12: Venda de Serviço | E12: 3602.18 | F12: Atrasado
B13: 46115 | C13: Entrada - Cliente B | D13: Venda de Serviço | E13: 554.41 | F13: Atrasado
B14: 46116 | C14: Entrada - Cliente C | D14: Venda de Serviço | E14: 3367.37 | F14: Atrasado
B15: 46116 | C15: Entrada - Cliente A | D15: Venda de Serviço | E15: 3417.4 | F15: Atrasado
B16: 46117 | C16: Entrada - Cliente C | D16: Venda de Serviço | E16: 1974.84 | F16: Pendente
B17: 46117 | C17: Entrada - Cliente C | D17: Venda de Serviço | E17: 4647.99 | F17: Pendente
B18: 46119 | C18: Entrada - Cliente B | D18: Venda de Serviço | E18: 3579.1 | F18: Atrasado
B19: 46120 | C19: Entrada - Cliente A | D19: Venda de Serviço | E19: 1852.9 | F19: Pendente
B20: 46122 | C20: Entrada - Cliente B | D20: Venda de Serviço | E20: 3115.94 | F20: Atrasado
B21: 46124 | C21: Entrada - Cliente C | D21: Venda de Serviço | E21: 2828.16 | F21: Atrasado
B22: 46130 | C22: Entrada - Cliente A | D22: Venda de Serviço | E22: 2563.02 | F22: Pendente
B23: 46131 | C23: Entrada - Cliente B | D23: Venda de Serviço | E23: 978.53 | F23: Pendente
... B83: 46290 | C83: Entrada - Cliente A | D83: Venda de Serviço | E83: 2782.36 | F83: Pendente
B86: Contas a pagar em aberto (64)
B87: Data | C87: Descrição | D87: Categoria | E87: Valor | F87: Status
B88: 46110 | C88: Saída - Fornecedor Z | D88: Imposto | E88: 849.83 | F88: Pendente
B89: 46111 | C89: Saída - Fornecedor Y | D89: Manutenção | E89: 665.55 | F89: Pendente
B90: 46112 | C90: Saída - Fornecedor Y | D90: Salário | E90: 3351.12 | F90: Pendente
B91: 46121 | C91: Saída - Fornecedor Y | D91: Imposto | E91: 3540.88 | F91: Atrasado
B92: 46123 | C92: Saída - Fornecedor Z | D92: Aluguel | E92: 4325.99 | F92: Atrasado
B93: 46123 | C93: Saída - Fornecedor X | D93: Fornecedor | E93: 2497.17 | F93: Atrasado
B94: 46125 | C94: Saída - Fornecedor Z | D94: Aluguel | E94: 3324.53 | F94: Pendente
B95: 46126 | C95: Saída - Fornecedor Y | D95: Salário | E95: 4328.55 | F95: Atrasado
B96: 46126 | C96: Saída - Fornecedor Y | D96: Imposto | E96: 1102.5 | F96: Pendente
B97: 46132 | C97: Saída - Fornecedor Z | D97: Salário | E97: 440.06 | F97: Pendente
B98: 46135 | C98: Saída - Fornecedor Y | D98: Salário | E98: 1761.15 | F98: Atrasado
B99: 46139 | C99: Saída - Fornecedor X | D99: Fornecedor | E99: 4710.28 | F99: Atrasado
... B151: 46290 | C151: Saída - Fornecedor Y | D151: Fornecedor | E151: 4517.09 | F151: Pendente

Sheet DRE
B1: DRE simplificado
B2: Demonstrativo de resultado · regime de competência: todas as transações lançadas, pagas ou não
B4: Receita bruta (entradas) | C4: =SUMIFS(Dados!$F$5:$F$204,Dados!$E$5:$E$204,"Entrada") -> 305963.76 | E4: Despesas por categoria
B5: Despesas operacionais
B6: Aluguel | C6: =SUMIFS(Dados!$F$5:$F$204,Dados!$E$5:$E$204,"Saída",Dados!$D$5:$D$204,"Aluguel") -> 26246.34
B7: Fornecedor | C7: =SUMIFS(Dados!$F$5:$F$204,Dados!$E$5:$E$204,"Saída",Dados!$D$5:$D$204,"Fornecedor") -> 46762.05
B8: Imposto | C8: =SUMIFS(Dados!$F$5:$F$204,Dados!$E$5:$E$204,"Saída",Dados!$D$5:$D$204,"Imposto") -> 68429.45
B9: Manutenção | C9: =SUMIFS(Dados!$F$5:$F$204,Dados!$E$5:$E$204,"Saída",Dados!$D$5:$D$204,"Manutenção") -> 28808.36
B10: Marketing | C10: =SUMIFS(Dados!$F$5:$F$204,Dados!$E$5:$E$204,"Saída",Dados!$D$5:$D$204,"Marketing") -> 25904.33
B11: Salário | C11: =SUMIFS(Dados!$F$5:$F$204,Dados!$E$5:$E$204,"Saída",Dados!$D$5:$D$204,"Salário") -> 47849.25
B12: Total de despesas | C12: =SUM(C6:C11) -> 243999.78
B14: Resultado líquido | C14: =C4-C12 -> 61963.98
B15: Margem líquida | C15: =C14/C4 -> 0.20252065
