Workbook

Sheet Resumo
A1: Dashboard Financeiro — PME
A2: Período: Mar/2026 a Sep/2026 · dados tratados a partir de um export bruto simulado (ver README)
A4: RECEBIDO (CAIXA) | D4: PAGO (CAIXA) | G4: SALDO DE CAIXA
A5: ='Fluxo Mensal'!B12 -> 82976.55 | D5: ='Fluxo Mensal'!C12 -> 61639.3 | G5: ='Fluxo Mensal'!D12 -> 21337.25
A7: CONTAS A RECEBER (EM ABERTO) | D7: CONTAS A PAGAR (EM ABERTO) | G7: RESULTADO LÍQUIDO (DRE)
A8: ='Contas a Pagar e Receber'!D5 -> 199712.9 | D8: ='Contas a Pagar e Receber'!D6 -> 177687.16 | G8: =DRE!B14 -> 61963.98
A10: Fluxo de caixa mensal
A28: Dados tratados a partir de um export financeiro simulado com sujeira proposital (categorias, datas, sinais e status) — ver README do projeto para o pipeline completo de tratamento e o relatório de qualidade de dados.

Sheet Dados
A1: Data | B1: Descrição | C1: Categoria | D1: Tipo | E1: Valor | F1: Status
A2: 46110 | B2: Saída - Fornecedor Z | C2: Imposto | D2: Saída | E2: 849.83 | F2: Pendente
A3: 46111 | B3: Saída - Fornecedor Y | C3: Manutenção | D3: Saída | E3: 665.55 | F3: Pendente
A4: 46112 | B4: Saída - Fornecedor Y | C4: Salário | D4: Saída | E4: 3351.12 | F4: Pendente
A5: 46113 | B5: Entrada - Cliente B | C5: Venda de Serviço | D5: Entrada | E5: 796.61 | F5: Pago
A6: 46115 | B6: Entrada - Cliente A | C6: Venda de Serviço | D6: Entrada | E6: 3602.18 | F6: Atrasado
A7: 46115 | B7: Entrada - Cliente B | C7: Venda de Serviço | D7: Entrada | E7: 554.41 | F7: Atrasado
A8: 46116 | B8: Entrada - Cliente C | C8: Venda de Serviço | D8: Entrada | E8: 3367.37 | F8: Atrasado
A9: 46116 | B9: Entrada - Cliente A | C9: Venda de Serviço | D9: Entrada | E9: 3417.4 | F9: Atrasado
A10: 46117 | B10: Entrada - Cliente C | C10: Venda de Serviço | D10: Entrada | E10: 1974.84 | F10: Pendente
A11: 46117 | B11: Entrada - Cliente C | C11: Venda de Serviço | D11: Entrada | E11: 4647.99 | F11: Pendente
A12: 46119 | B12: Entrada - Cliente B | C12: Venda de Serviço | D12: Entrada | E12: 3579.1 | F12: Atrasado
A13: 46120 | B13: Entrada - Cliente A | C13: Venda de Serviço | D13: Entrada | E13: 1852.9 | F13: Pendente
... A201: 46290 | B201: Entrada - Cliente A | C201: Venda de Serviço | D201: Entrada | E201: 2782.36 | F201: Pendente

Sheet Fluxo Mensal
A1: Fluxo de Caixa Mensal
A2: Período: Mar/2026 a Sep/2026 · regime de caixa: só transações com status Pago (pendentes/atrasadas ficam em Contas a Pagar e Receber)
A4: Mês | B4: Entradas | C4: Saídas | D4: Saldo do Mês | E4: Saldo Acumulado
A5: 46082 | B5: =SUMIFS(Dados!$E$2:$E$201,Dados!$D$2:$D$201,"Entrada",Dados!$F$2:$F$201,"Pago",Dados!$A$2:$A$201,">="&A5,Dados!$A$2:$A$201,"<"&EDATE(A5,1)) -> 0 | C5: =SUMIFS(Dados!$E$2:$E$201,Dados!$D$2:$D$201,"Saída",Dados!$F$2:$F$201,"Pago",Dados!$A$2:$A$201,">="&A5,Dados!$A$2:$A$201,"<"&EDATE(A5,1)) -> 0 | D5: =B5-C5 -> 0 | E5: =D5 -> 0
A6: 46113 | B6: =SUMIFS(Dados!$E$2:$E$201,Dados!$D$2:$D$201,"Entrada",Dados!$F$2:$F$201,"Pago",Dados!$A$2:$A$201,">="&A6,Dados!$A$2:$A$201,"<"&EDATE(A6,1)) -> 17510.88 | C6: =SUMIFS(Dados!$E$2:$E$201,Dados!$D$2:$D$201,"Saída",Dados!$F$2:$F$201,"Pago",Dados!$A$2:$A$201,">="&A6,Dados!$A$2:$A$201,"<"&EDATE(A6,1)) -> 3978.99 | D6: =B6-C6 -> 13531.89 | E6: =E5+D6 -> 13531.89
A7: 46143 | B7: =SUMIFS(Dados!$E$2:$E$201,Dados!$D$2:$D$201,"Entrada",Dados!$F$2:$F$201,"Pago",Dados!$A$2:$A$201,">="&A7,Dados!$A$2:$A$201,"<"&EDATE(A7,1)) -> 13227.69 | C7: =SUMIFS(Dados!$E$2:$E$201,Dados!$D$2:$D$201,"Saída",Dados!$F$2:$F$201,"Pago",Dados!$A$2:$A$201,">="&A7,Dados!$A$2:$A$201,"<"&EDATE(A7,1)) -> 9067.97 | D7: =B7-C7 -> 4159.72 | E7: =E6+D7 -> 17691.61
A8: 46174 | B8: =SUMIFS(Dados!$E$2:$E$201,Dados!$D$2:$D$201,"Entrada",Dados!$F$2:$F$201,"Pago",Dados!$A$2:$A$201,">="&A8,Dados!$A$2:$A$201,"<"&EDATE(A8,1)) -> 10106.95 | C8: =SUMIFS(Dados!$E$2:$E$201,Dados!$D$2:$D$201,"Saída",Dados!$F$2:$F$201,"Pago",Dados!$A$2:$A$201,">="&A8,Dados!$A$2:$A$201,"<"&EDATE(A8,1)) -> 0 | D8: =B8-C8 -> 10106.95 | E8: =E7+D8 -> 27798.56
A9: 46204 | B9: =SUMIFS(Dados!$E$2:$E$201,Dados!$D$2:$D$201,"Entrada",Dados!$F$2:$F$201,"Pago",Dados!$A$2:$A$201,">="&A9,Dados!$A$2:$A$201,"<"&EDATE(A9,1)) -> 15254.72 | C9: =SUMIFS(Dados!$E$2:$E$201,Dados!$D$2:$D$201,"Saída",Dados!$F$2:$F$201,"Pago",Dados!$A$2:$A$201,">="&A9,Dados!$A$2:$A$201,"<"&EDATE(A9,1)) -> 24986.93 | D9: =B9-C9 -> -9732.21 | E9: =E8+D9 -> 18066.35
A10: 46235 | B10: =SUMIFS(Dados!$E$2:$E$201,Dados!$D$2:$D$201,"Entrada",Dados!$F$2:$F$201,"Pago",Dados!$A$2:$A$201,">="&A10,Dados!$A$2:$A$201,"<"&EDATE(A10,1)) -> 14949.33 | C10: =SUMIFS(Dados!$E$2:$E$201,Dados!$D$2:$D$201,"Saída",Dados!$F$2:$F$201,"Pago",Dados!$A$2:$A$201,">="&A10,Dados!$A$2:$A$201,"<"&EDATE(A10,1)) -> 6810.78 | D10: =B10-C10 -> 8138.55 | E10: =E9+D10 -> 26204.9
A11: 46266 | B11: =SUMIFS(Dados!$E$2:$E$201,Dados!$D$2:$D$201,"Entrada",Dados!$F$2:$F$201,"Pago",Dados!$A$2:$A$201,">="&A11,Dados!$A$2:$A$201,"<"&EDATE(A11,1)) -> 11926.98 | C11: =SUMIFS(Dados!$E$2:$E$201,Dados!$D$2:$D$201,"Saída",Dados!$F$2:$F$201,"Pago",Dados!$A$2:$A$201,">="&A11,Dados!$A$2:$A$201,"<"&EDATE(A11,1)) -> 16794.63 | D11: =B11-C11 -> -4867.65 | E11: =E10+D11 -> 21337.25
A12: Total | B12: =SUM(B5:B11) -> 82976.55 | C12: =SUM(C5:C11) -> 61639.3 | D12: =SUM(D5:D11) -> 21337.25

Sheet Contas a Pagar e Receber
A1: Contas a Pagar e Receber
A2: Transações com status Pendente ou Atrasado (em aberto)
B4: Pendente | C4: Atrasado | D4: Total em Aberto
A5: A Receber (Entradas) | B5: =SUMIFS(Dados!$E$2:$E$201,Dados!$D$2:$D$201,"Entrada",Dados!$F$2:$F$201,"Pendente") -> 86550.82 | C5: =SUMIFS(Dados!$E$2:$E$201,Dados!$D$2:$D$201,"Entrada",Dados!$F$2:$F$201,"Atrasado") -> 113162.08 | D5: =B5+C5 -> 199712.9
A6: A Pagar (Saídas) | B6: =SUMIFS(Dados!$E$2:$E$201,Dados!$D$2:$D$201,"Saída",Dados!$F$2:$F$201,"Pendente") -> 84201.8 | C6: =SUMIFS(Dados!$E$2:$E$201,Dados!$D$2:$D$201,"Saída",Dados!$F$2:$F$201,"Atrasado") -> 93485.36 | D6: =B6+C6 -> 177687.16
A7: Saldo em Aberto (Receber − Pagar) | D7: =D5-D6 -> 22025.74
A10: Contas a Receber em Aberto (72 transações) | G10: Contas a Pagar em Aberto (64 transações)
A11: Data | B11: Descrição | C11: Categoria | D11: Valor | E11: Status | G11: Data | H11: Descrição | I11: Categoria | J11: Valor | K11: Status
A12: 46115 | B12: Entrada - Cliente A | C12: Venda de Serviço | D12: 3602.18 | E12: Atrasado | G12: 46110 | H12: Saída - Fornecedor Z | I12: Imposto | J12: 849.83 | K12: Pendente
A13: 46115 | B13: Entrada - Cliente B | C13: Venda de Serviço | D13: 554.41 | E13: Atrasado | G13: 46111 | H13: Saída - Fornecedor Y | I13: Manutenção | J13: 665.55 | K13: Pendente
A14: 46116 | B14: Entrada - Cliente C | C14: Venda de Serviço | D14: 3367.37 | E14: Atrasado | G14: 46112 | H14: Saída - Fornecedor Y | I14: Salário | J14: 3351.12 | K14: Pendente
A15: 46116 | B15: Entrada - Cliente A | C15: Venda de Serviço | D15: 3417.4 | E15: Atrasado | G15: 46121 | H15: Saída - Fornecedor Y | I15: Imposto | J15: 3540.88 | K15: Atrasado
A16: 46117 | B16: Entrada - Cliente C | C16: Venda de Serviço | D16: 1974.84 | E16: Pendente | G16: 46123 | H16: Saída - Fornecedor Z | I16: Aluguel | J16: 4325.99 | K16: Atrasado
A17: 46117 | B17: Entrada - Cliente C | C17: Venda de Serviço | D17: 4647.99 | E17: Pendente | G17: 46123 | H17: Saída - Fornecedor X | I17: Fornecedor | J17: 2497.17 | K17: Atrasado
A18: 46119 | B18: Entrada - Cliente B | C18: Venda de Serviço | D18: 3579.1 | E18: Atrasado | G18: 46125 | H18: Saída - Fornecedor Z | I18: Aluguel | J18: 3324.53 | K18: Pendente
A19: 46120 | B19: Entrada - Cliente A | C19: Venda de Serviço | D19: 1852.9 | E19: Pendente | G19: 46126 | H19: Saída - Fornecedor Y | I19: Salário | J19: 4328.55 | K19: Atrasado
A20: 46122 | B20: Entrada - Cliente B | C20: Venda de Serviço | D20: 3115.94 | E20: Atrasado | G20: 46126 | H20: Saída - Fornecedor Y | I20: Imposto | J20: 1102.5 | K20: Pendente
A21: 46124 | B21: Entrada - Cliente C | C21: Venda de Serviço | D21: 2828.16 | E21: Atrasado | G21: 46132 | H21: Saída - Fornecedor Z | I21: Salário | J21: 440.06 | K21: Pendente
A22: 46130 | B22: Entrada - Cliente A | C22: Venda de Serviço | D22: 2563.02 | E22: Pendente | G22: 46135 | H22: Saída - Fornecedor Y | I22: Salário | J22: 1761.15 | K22: Atrasado
A23: 46131 | B23: Entrada - Cliente B | C23: Venda de Serviço | D23: 978.53 | E23: Pendente | G23: 46139 | H23: Saída - Fornecedor X | I23: Fornecedor | J23: 4710.28 | K23: Atrasado
... A75: 46261 | B75: Entrada - Cliente B | C75: Venda de Serviço | D75: 1606.86 | E75: Pendente | G75: 46290 | H75: Saída - Fornecedor Y | I75: Fornecedor | J75: 4517.09 | K75: Pendente
A76: 46261 | B76: Entrada - Cliente C | C76: Venda de Serviço | D76: 674.79 | E76: Atrasado
A77: 46263 | B77: Entrada - Cliente B | C77: Venda de Serviço | D77: 4255.4 | E77: Pendente
A78: 46264 | B78: Entrada - Cliente C | C78: Venda de Serviço | D78: 3426.23 | E78: Pendente
A79: 46272 | B79: Entrada - Cliente A | C79: Venda de Serviço | D79: 2962.78 | E79: Atrasado
A80: 46273 | B80: Entrada - Cliente B | C80: Venda de Serviço | D80: 473.98 | E80: Atrasado
A81: 46278 | B81: Entrada - Cliente A | C81: Venda de Serviço | D81: 3752.48 | E81: Atrasado
A82: 46279 | B82: Entrada - Cliente B | C82: Venda de Serviço | D82: 4287.26 | E82: Pendente
A83: 46290 | B83: Entrada - Cliente A | C83: Venda de Serviço | D83: 2782.36 | E83: Pendente

Sheet DRE
A1: DRE Simplificado
A2: Demonstrativo de Resultado — regime de competência (todas as transações lançadas, pagas ou não)
A4: Receita Bruta (Entradas) | B4: =SUMIFS(Dados!$E$2:$E$201,Dados!$D$2:$D$201,"Entrada") -> 305963.76
A5: Despesas Operacionais
A6: Aluguel | B6: =SUMIFS(Dados!$E$2:$E$201,Dados!$D$2:$D$201,"Saída",Dados!$C$2:$C$201,"Aluguel") -> 26246.34
A7: Fornecedor | B7: =SUMIFS(Dados!$E$2:$E$201,Dados!$D$2:$D$201,"Saída",Dados!$C$2:$C$201,"Fornecedor") -> 46762.05
A8: Imposto | B8: =SUMIFS(Dados!$E$2:$E$201,Dados!$D$2:$D$201,"Saída",Dados!$C$2:$C$201,"Imposto") -> 68429.45
A9: Manutenção | B9: =SUMIFS(Dados!$E$2:$E$201,Dados!$D$2:$D$201,"Saída",Dados!$C$2:$C$201,"Manutenção") -> 28808.36
A10: Marketing | B10: =SUMIFS(Dados!$E$2:$E$201,Dados!$D$2:$D$201,"Saída",Dados!$C$2:$C$201,"Marketing") -> 25904.33
A11: Salário | B11: =SUMIFS(Dados!$E$2:$E$201,Dados!$D$2:$D$201,"Saída",Dados!$C$2:$C$201,"Salário") -> 47849.25
A12: Total de Despesas | B12: =SUM(B6:B11) -> 243999.78
A14: Resultado Líquido | B14: =B4-B12 -> 61963.98
A15: Margem Líquida | B15: =B14/B4 -> 0.20252065
